tesxcel/__init__.py
tesxcel/_excel.py
tesxcel/version.py
tesxcel-3.0.0.dist-info/LICENSE
tesxcel-3.0.0.dist-info/METADATA
tesxcel-3.0.0.dist-info/WHEEL
tesxcel-3.0.0.dist-info/top_level.txt
tesxcel-3.0.0.dist-info/RECORD
